lwdia/__init__.py
lwdia/settings.py
lwdia/core/__init__.py
lwdia/core/lwdia.py
lwdia/dirs/__init__.py
lwdia/exception/__init__.py
lwdia/implements/__init__.py
lwdia/locale/__init__.py
lwdia/locale/en_US/LC_MESSAGES/lwdia.mo
lwdia/locale/en_US/LC_MESSAGES/primaryschool.mo
lwdia/locale/zh_CN/LC_MESSAGES/lwdia.mo
lwdia/locale/zh_CN/LC_MESSAGES/primaryschool.mo
lwdia/ready/__init__.py
lwdia/resource/__init__.py
lwdia/widgets/__init__.py
lwdia/widgets/areabase.py
lwdia/widgets/combinationarea.py
lwdia/widgets/common.py
lwdia/widgets/examplearea.py
lwdia/widgets/mainwindow.py
lwdia/widgets/presentationarea.py
lwdia/widgets/runwindow.py
lwdia/widgets/scrollbar.py
lwdia/widgets/toolbar.py
lwdia/widgets/gratchwidgets/__init__.py
lwdia/widgets/gratchwidgets/startwidget.py
lwdia/widgets/gratchwidgets/widgetbase.py
tests/__init__.py
lwdia-0.0.2.dist-info/LICENSE
lwdia-0.0.2.dist-info/METADATA
lwdia-0.0.2.dist-info/WHEEL
lwdia-0.0.2.dist-info/entry_points.txt
lwdia-0.0.2.dist-info/top_level.txt
lwdia-0.0.2.dist-info/RECORD
